Workbook
Name Slicer_Department: #N/A
Name Slicer_Education_Field2: #N/A
Name Slicer_Gender1: #N/A

Sheet KPI
A3: Count of Employee Number | B3: Average of Age | C3: Sum of CF_attrition count
A4: 1470 | B4: 36.92381 | C4: 237
A7: Total Employee | B7: Average Age | C7: Attrition Count | D7: Active employee | E7: Atrrition Rate
A8: =GETPIVOTDATA("Count of Employee Number",$A$3) -> 1470 | B8: =GETPIVOTDATA("Average of Age",$A$3) -> 36.92381 | C8: =GETPIVOTDATA("Sum of CF_attrition count",$A$3) -> 237 | D8: =A8-C8 -> 1233 | E8: =C8/A8 -> 0.16122449

Sheet Rating
A3: Average of Job Satisfaction
A4: 2.6265306
A7: Rating | B7: =GETPIVOTDATA("Job Satisfaction",$A$3) -> 2.6265306 | C7: =B7/4 -> 0.65663265
A8: Balance Rating | B8: =4-B7 -> 1.3734694 | C8: =B8/4 -> 0.34336735

Sheet Gender
A3: Row Labels | B3: Count of Employee Count
A4: Female | B4: 588
A5: Male | B5: 882
A6: Grand Total | B6: 1470
A9: Female | B9: =IFERROR(GETPIVOTDATA("Employee Count",$A$3,"Gender","Female"),0) -> 588 | C9: =IFERROR(B9/($B$9+$B$10),0) -> 0.4
A10: Male | B10: =IFERROR(GETPIVOTDATA("Employee Count",$A$3,"Gender","Male"),0) -> 882 | C10: =IFERROR(B10/($B$10+$B$9),0) -> 0.6

Sheet EducationByAttrition
A3: Education | B3: Sum of CF_attrition count
A4: Doctoral Degree | B4: 5
A5: High School | B5: 31
A6: Associates Degree | B6: 44
A7: Master's Degree | B7: 58
A8: Bachelor's Degree | B8: 99
A9: Grand Total | B9: 237

Sheet AttritionByJob
A3: Job Role | B3: Sum of CF_attrition count | D3: Job Role | E3: Attrition
A4: Healthcare Representative | B4: 9 | D4: =A4 -> Healthcare Representative | E4: =GETPIVOTDATA("CF_attrition count",$A$3,"Job Role",A4) -> 9
A5: Human Resources | B5: 12 | D5: =A5 -> Human Resources | E5: =GETPIVOTDATA("CF_attrition count",$A$3,"Job Role",A5) -> 12
A6: Laboratory Technician | B6: 62 | D6: =A6 -> Laboratory Technician | E6: =GETPIVOTDATA("CF_attrition count",$A$3,"Job Role",A6) -> 62
A7: Manager | B7: 5 | D7: =A7 -> Manager | E7: =GETPIVOTDATA("CF_attrition count",$A$3,"Job Role",A7) -> 5
A8: Manufacturing Director | B8: 10 | D8: =A8 -> Manufacturing Director | E8: =GETPIVOTDATA("CF_attrition count",$A$3,"Job Role",A8) -> 10
A9: Research Director | B9: 2 | D9: =A9 -> Research Director | E9: =GETPIVOTDATA("CF_attrition count",$A$3,"Job Role",A9) -> 2
A10: Research Scientist | B10: 47 | D10: =A10 -> Research Scientist | E10: =GETPIVOTDATA("CF_attrition count",$A$3,"Job Role",A10) -> 47
A11: Sales Executive | B11: 57 | D11: =A11 -> Sales Executive | E11: =GETPIVOTDATA("CF_attrition count",$A$3,"Job Role",A11) -> 57
A12: Sales Representative | B12: 33 | D12: =A12 -> Sales Representative | E12: =GETPIVOTDATA("CF_attrition count",$A$3,"Job Role",A12) -> 33
A13: Grand Total | B13: 237

Sheet DepartmentWiseAttrition
A3: Department | B3: Sum of CF_attrition count
A4: HR | B4: 0.050632911
A5: R&D | B5: 0.56118143
A6: Sales | B6: 0.38818565
A7: Grand Total | B7: 1

Sheet AttritionByAgeGroup
A3: CF_age band | B3: Sum of CF_attrition count
A4: 25 - 34 | B4: 112
A5: 35 - 44 | B5: 51
A6: Under 25 | B6: 38
A7: 45 - 54 | B7: 25
A8: Over 55 | B8: 11
A9: Grand Total | B9: 237

Sheet AttritionByMaritalStatus
A3: Marital Status | B3: Count of Attrition | D3: Marital Status | E3: Atrrition
A4: Divorced | B4: 327 | D4: =A4 -> Divorced | E4: =GETPIVOTDATA("Attrition",$A$3,"Marital Status",A4) -> 327
A5: Single | B5: 470 | D5: =A5 -> Single | E5: =GETPIVOTDATA("Attrition",$A$3,"Marital Status",A5) -> 470
A6: Married | B6: 673 | D6: =A6 -> Married | E6: =GETPIVOTDATA("Attrition",$A$3,"Marital Status",A6) -> 673
A7: Grand Total | B7: 1470

Sheet Data
A1: Attrition | B1: Business Travel | C1: CF_age band | D1: CF_attrition label | E1: Department | F1: Education Field | G1: emp no | H1: Employee Number | I1: Gender | J1: Job Role | K1: Marital Status | L1: Over Time | M1: Over18 | N1: Training Times Last Year | O1: -2 | P1: 0 | Q1: Age | R1: CF_attrition count | S1: CF_attrition counts | T1: CF_attrition rate | U1: CF_current Employee | V1: Daily Rate | W1: Distance From Home | X1: Education | Y1: Employee Count | Z1: Environment Satisfaction | AA1: Hourly Rate | AB1: Job Involvement | AC1: Job Level | AD1: Job Satisfaction | AE1: Monthly Income | AF1: Monthly Rate | AG1: Num Companies Worked | AH1: Percent Salary Hike | AI1: Performance Rating | AJ1: Relationship Satisfaction | AK1: Standard Hours | AL1: Stock Option Level | AM1: Total Working Years | AN1: Work Life Balance | AO1: Years At Company | AP1: Years In Current Role | AQ1: Years Since Last Promotion | AR1: Years With Curr Manager
A2: Yes | B2: Travel_Rarely | C2: 35 - 44 | D2: Ex-Employees | E2: Sales | F2: Life Sciences | G2: STAFF-1 | H2: 1 | I2: Female | J2: Sales Executive | K2: Single | L2: Yes | M2: Y | N2: 0 | O2: -2 | P2: 0 | Q2: 41 | R2: 1 | S2: 1 | T2: 1 | U2: 0 | V2: 1102 | W2: 1 | X2: Associates Degree | Y2: 1 | Z2: 2 | AA2: 94 | AB2: 3 | AC2: 2 | AD2: 4 | AE2: 5993 | AF2: 19479 | AG2: 8 | AH2: 11 | AI2: 3 | AJ2: 1 | AK2: 80 | AL2: 0 | AM2: 8 | AN2: 1 | AO2: 6 | AP2: 4 | AQ2: 0 | AR2: 5
A3: No | B3: Travel_Frequently | C3: 45 - 54 | D3: Current Employees | E3: R&D | F3: Life Sciences | G3: STAFF-2 | H3: 2 | I3: Male | J3: Research Scientist | K3: Married | L3: No | M3: Y | N3: 3 | O3: -2 | P3: 0 | Q3: 49 | R3: 0 | T3: 0 | U3: 1 | V3: 279 | W3: 8 | X3: High School | Y3: 1 | Z3: 3 | AA3: 61 | AB3: 2 | AC3: 2 | AD3: 2 | AE3: 5130 | AF3: 24907 | AG3: 1 | AH3: 23 | AI3: 4 | AJ3: 4 | AK3: 80 | AL3: 1 | AM3: 10 | AN3: 3 | AO3: 10 | AP3: 7 | AQ3: 1 | AR3: 7
A4: Yes | B4: Travel_Rarely | C4: 35 - 44 | D4: Ex-Employees | E4: R&D | F4: Other | G4: STAFF-4 | H4: 4 | I4: Male | J4: Laboratory Technician | K4: Single | L4: Yes | M4: Y | N4: 3 | O4: -2 | P4: 0 | Q4: 37 | R4: 1 | S4: 1 | T4: 1 | U4: 0 | V4: 1373 | W4: 2 | X4: Associates Degree | Y4: 1 | Z4: 4 | AA4: 92 | AB4: 2 | AC4: 1 | AD4: 3 | AE4: 2090 | AF4: 2396 | AG4: 6 | AH4: 15 | AI4: 3 | AJ4: 2 | AK4: 80 | AL4: 0 | AM4: 7 | AN4: 3 | AO4: 0 | AP4: 0 | AQ4: 0 | AR4: 0
A5: No | B5: Travel_Frequently | C5: 25 - 34 | D5: Current Employees | E5: R&D | F5: Life Sciences | G5: STAFF-5 | H5: 5 | I5: Female | J5: Research Scientist | K5: Married | L5: Yes | M5: Y | N5: 3 | O5: -2 | P5: 0 | Q5: 33 | R5: 0 | T5: 0 | U5: 1 | V5: 1392 | W5: 3 | X5: Master's Degree | Y5: 1 | Z5: 4 | AA5: 56 | AB5: 3 | AC5: 1 | AD5: 3 | AE5: 2909 | AF5: 23159 | AG5: 1 | AH5: 11 | AI5: 3 | AJ5: 3 | AK5: 80 | AL5: 0 | AM5: 8 | AN5: 3 | AO5: 8 | AP5: 7 | AQ5: 3 | AR5: 0
A6: No | B6: Travel_Rarely | C6: 25 - 34 | D6: Current Employees | E6: R&D | F6: Medical | G6: STAFF-7 | H6: 7 | I6: Male | J6: Laboratory Technician | K6: Married | L6: No | M6: Y | N6: 3 | O6: -2 | P6: 0 | Q6: 27 | R6: 0 | T6: 0 | U6: 1 | V6: 591 | W6: 2 | X6: High School | Y6: 1 | Z6: 1 | AA6: 40 | AB6: 3 | AC6: 1 | AD6: 2 | AE6: 3468 | AF6: 16632 | AG6: 9 | AH6: 12 | AI6: 3 | AJ6: 4 | AK6: 80 | AL6: 1 | AM6: 6 | AN6: 3 | AO6: 2 | AP6: 2 | AQ6: 2 | AR6: 2
A7: No | B7: Travel_Frequently | C7: 25 - 34 | D7: Current Employees | E7: R&D | F7: Life Sciences | G7: STAFF-8 | H7: 8 | I7: Male | J7: Laboratory Technician | K7: Single | L7: No | M7: Y | N7: 2 | O7: -2 | P7: 0 | Q7: 32 | R7: 0 | T7: 0 | U7: 1 | V7: 1005 | W7: 2 | X7: Associates Degree | Y7: 1 | Z7: 4 | AA7: 79 | AB7: 3 | AC7: 1 | AD7: 2 | AE7: 3068 | AF7: 11864 | AG7: 0 | AH7: 13 | AI7: 3 | AJ7: 3 | AK7: 80 | AL7: 0 | AM7: 8 | AN7: 2 | AO7: 7 | AP7: 7 | AQ7: 3 | AR7: 6
A8: No | B8: Travel_Rarely | C8: Over 55 | D8: Current Employees | E8: R&D | F8: Medical | G8: STAFF-10 | H8: 10 | I8: Female | J8: Laboratory Technician | K8: Married | L8: Yes | M8: Y | N8: 3 | O8: -2 | P8: 0 | Q8: 59 | R8: 0 | T8: 0 | U8: 1 | V8: 1324 | W8: 3 | X8: Bachelor's Degree | Y8: 1 | Z8: 3 | AA8: 81 | AB8: 4 | AC8: 1 | AD8: 4 | AE8: 2670 | AF8: 9964 | AG8: 4 | AH8: 20 | AI8: 4 | AJ8: 1 | AK8: 80 | AL8: 3 | AM8: 12 | AN8: 2 | AO8: 1 | AP8: 0 | AQ8: 0 | AR8: 0
A9: No | B9: Travel_Rarely | C9: 25 - 34 | D9: Current Employees | E9: R&D | F9: Life Sciences | G9: STAFF-11 | H9: 11 | I9: Male | J9: Laboratory Technician | K9: Divorced | L9: No | M9: Y | N9: 2 | O9: -2 | P9: 0 | Q9: 30 | R9: 0 | T9: 0 | U9: 1 | V9: 1358 | W9: 24 | X9: High School | Y9: 1 | Z9: 4 | AA9: 67 | AB9: 3 | AC9: 1 | AD9: 2 | AE9: 2693 | AF9: 13335 | AG9: 1 | AH9: 22 | AI9: 4 | AJ9: 2 | AK9: 80 | AL9: 1 | AM9: 1 | AN9: 3 | AO9: 1 | AP9: 0 | AQ9: 0 | AR9: 0
A10: No | B10: Travel_Frequently | C10: 35 - 44 | D10: Current Employees | E10: R&D | F10: Life Sciences | G10: STAFF-12 | H10: 12 | I10: Male | J10: Manufacturing Director | K10: Single | L10: No | M10: Y | N10: 2 | O10: -2 | P10: 0 | Q10: 38 | R10: 0 | T10: 0 | U10: 1 | V10: 216 | W10: 23 | X10: Bachelor's Degree | Y10: 1 | Z10: 4 | AA10: 44 | AB10: 2 | AC10: 3 | AD10: 2 | AE10: 9526 | AF10: 8787 | AG10: 0 | AH10: 21 | AI10: 4 | AJ10: 2 | AK10: 80 | AL10: 0 | AM10: 10 | AN10: 3 | AO10: 9 | AP10: 7 | AQ10: 1 | AR10: 8
A11: No | B11: Travel_Rarely | C11: 35 - 44 | D11: Current Employees | E11: R&D | F11: Medical | G11: STAFF-13 | H11: 13 | I11: Male | J11: Healthcare Representative | K11: Married | L11: No | M11: Y | N11: 3 | O11: -2 | P11: 0 | Q11: 36 | R11: 0 | T11: 0 | U11: 1 | V11: 1299 | W11: 27 | X11: Bachelor's Degree | Y11: 1 | Z11: 3 | AA11: 94 | AB11: 3 | AC11: 2 | AD11: 3 | AE11: 5237 | AF11: 16577 | AG11: 6 | AH11: 13 | AI11: 3 | AJ11: 2 | AK11: 80 | AL11: 2 | AM11: 17 | AN11: 2 | AO11: 7 | AP11: 7 | AQ11: 7 | AR11: 7
A12: No | B12: Travel_Rarely | C12: 35 - 44 | D12: Current Employees | E12: R&D | F12: Medical | G12: STAFF-14 | H12: 14 | I12: Male | J12: Laboratory Technician | K12: Married | L12: No | M12: Y | N12: 5 | O12: -2 | P12: 0 | Q12: 35 | R12: 0 | T12: 0 | U12: 1 | V12: 809 | W12: 16 | X12: Bachelor's Degree | Y12: 1 | Z12: 1 | AA12: 84 | AB12: 4 | AC12: 1 | AD12: 2 | AE12: 2426 | AF12: 16479 | AG12: 0 | AH12: 13 | AI12: 3 | AJ12: 3 | AK12: 80 | AL12: 1 | AM12: 6 | AN12: 3 | AO12: 5 | AP12: 4 | AQ12: 0 | AR12: 3
A13: No | B13: Travel_Rarely | C13: 25 - 34 | D13: Current Employees | E13: R&D | F13: Life Sciences | G13: STAFF-15 | H13: 15 | I13: Female | J13: Laboratory Technician | K13: Single | L13: Yes | M13: Y | N13: 3 | O13: -2 | P13: 0 | Q13: 29 | R13: 0 | T13: 0 | U13: 1 | V13: 153 | W13: 15 | X13: Associates Degree | Y13: 1 | Z13: 4 | AA13: 49 | AB13: 2 | AC13: 2 | AD13: 2 | AE13: 4193 | AF13: 12682 | AG13: 0 | AH13: 12 | AI13: 3 | AJ13: 4 | AK13: 80 | AL13: 0 | AM13: 10 | AN13: 3 | AO13: 9 | AP13: 5 | AQ13: 0 | AR13: 8
A14: No | B14: Travel_Rarely | C14: 25 - 34 | D14: Current Employees | E14: R&D | F14: Life Sciences | G14: STAFF-16 | H14: 16 | I14: Male | J14: Research Scientist | K14: Divorced | L14: No | M14: Y | N14: 1 | O14: -2 | P14: 0 | Q14: 31 | R14: 0 | T14: 0 | U14: 1 | V14: 670 | W14: 26 | X14: High School | Y14: 1 | Z14: 1 | AA14: 31 | AB14: 3 | AC14: 1 | AD14: 2 | AE14: 2911 | AF14: 15170 | AG14: 1 | AH14: 17 | AI14: 3 | AJ14: 4 | AK14: 80 | AL14: 1 | AM14: 5 | AN14: 2 | AO14: 5 | AP14: 2 | AQ14: 4 | AR14: 3
A15: No | B15: Travel_Rarely | C15: 25 - 34 | D15: Current Employees | E15: R&D | F15: Medical | G15: STAFF-18 | H15: 18 | I15: Male | J15: Laboratory Technician | K15: Divorced | L15: No | M15: Y | N15: 2 | O15: -2 | P15: 0 | Q15: 34 | R15: 0 | T15: 0 | U15: 1 | V15: 1346 | W15: 19 | X15: Associates Degree | Y15: 1 | Z15: 2 | AA15: 93 | AB15: 3 | AC15: 1 | AD15: 4 | AE15: 2661 | AF15: 8758 | AG15: 0 | AH15: 11 | AI15: 3 | AJ15: 3 | AK15: 80 | AL15: 1 | AM15: 3 | AN15: 3 | AO15: 2 | AP15: 2 | AQ15: 1 | AR15: 2
A16: Yes | B16: Travel_Rarely | C16: 25 - 34 | D16: Ex-Employees | E16: R&D | F16: Life Sciences | G16: STAFF-19 | H16: 19 | I16: Male | J16: Laboratory Technician | K16: Single | L16: Yes | M16: Y | N16: 4 | O16: -2 | P16: 0 | Q16: 28 | R16: 1 | S16: 1 | T16: 1 | U16: 0 | V16: 103 | W16: 24 | X16: Bachelor's Degree | Y16: 1 | Z16: 3 | AA16: 50 | AB16: 2 | AC16: 1 | AD16: 2 | AE16: 2028 | AF16: 12947 | AG16: 5 | AH16: 14 | AI16: 3 | AJ16: 2 | AK16: 80 | AL16: 0 | AM16: 6 | AN16: 3 | AO16: 4 | AP16: 2 | AQ16: 0 | AR16: 3
A17: No | B17: Travel_Rarely | C17: 25 - 34 | D17: Current Employees | E17: R&D | F17: Life Sciences | G17: STAFF-20 | H17: 20 | I17: Female | J17: Manufacturing Director | K17: Divorced | L17: No | M17: Y | N17: 1 | O17: -2 | P17: 0 | Q17: 29 | R17: 0 | T17: 0 | U17: 1 | V17: 1389 | W17: 21 | X17: Master's Degree | Y17: 1 | Z17: 2 | AA17: 51 | AB17: 4 | AC17: 3 | AD17: 2 | AE17: 9980 | AF17: 10195 | AG17: 1 | AH17: 11 | AI17: 3 | AJ17: 3 | AK17: 80 | AL17: 1 | AM17: 10 | AN17: 3 | AO17: 10 | AP17: 9 | AQ17: 8 | AR17: 8
A18: No | B18: Travel_Rarely | C18: 25 - 34 | D18: Current Employees | E18: R&D | F18: Life Sciences | G18: STAFF-21 | H18: 21 | I18: Male | J18: Research Scientist | K18: Divorced | L18: Yes | M18: Y | N18: 5 | O18: -2 | P18: 0 | Q18: 32 | R18: 0 | T18: 0 | U18: 1 | V18: 334 | W18: 5 | X18: Associates Degree | Y18: 1 | Z18: 1 | AA18: 80 | AB18: 4 | AC18: 1 | AD18: 2 | AE18: 3298 | AF18: 15053 | AG18: 0 | AH18: 12 | AI18: 3 | AJ18: 4 | AK18: 80 | AL18: 2 | AM18: 7 | AN18: 2 | AO18: 6 | AP18: 2 | AQ18: 0 | AR18: 5
A19: No | B19: Non-Travel | C19: Under 25 | D19: Current Employees | E19: R&D | F19: Medical | G19: STAFF-22 | H19: 22 | I19: Male | J19: Laboratory Technician | K19: Divorced | L19: Yes | M19: Y | N19: 2 | O19: -2 | P19: 0 | Q19: 22 | R19: 0 | T19: 0 | U19: 1 | V19: 1123 | W19: 16 | X19: Associates Degree | Y19: 1 | Z19: 4 | AA19: 96 | AB19: 4 | AC19: 1 | AD19: 4 | AE19: 2935 | AF19: 7324 | AG19: 1 | AH19: 13 | AI19: 3 | AJ19: 2 | AK19: 80 | AL19: 2 | AM19: 1 | AN19: 2 | AO19: 1 | AP19: 0 | AQ19: 0 | AR19: 0
A20: No | B20: Travel_Rarely | C20: 45 - 54 | D20: Current Employees | E20: Sales | F20: Life Sciences | G20: STAFF-23 | H20: 23 | I20: Female | J20: Manager | K20: Married | L20: No | M20: Y | N20: 3 | O20: -2 | P20: 0 | Q20: 53 | R20: 0 | T20: 0 | U20: 1 | V20: 1219 | W20: 2 | X20: Master's Degree | Y20: 1 | Z20: 1 | AA20: 78 | AB20: 2 | AC20: 4 | AD20: 2 | AE20: 15427 | AF20: 22021 | AG20: 2 | AH20: 16 | AI20: 3 | AJ20: 3 | AK20: 80 | AL20: 0 | AM20: 31 | AN20: 3 | AO20: 25 | AP20: 8 | AQ20: 3 | AR20: 7
A21: No | B21: Travel_Rarely | C21: 35 - 44 | D21: Current Employees | E21: R&D | F21: Life Sciences | G21: STAFF-24 | H21: 24 | I21: Male | J21: Research Scientist | K21: Single | L21: Yes | M21: Y | N21: 3 | O21: -2 | P21: 0 | Q21: 38 | R21: 0 | T21: 0 | U21: 1 | V21: 371 | W21: 2 | X21: Bachelor's Degree | Y21: 1 | Z21: 4 | AA21: 45 | AB21: 3 | AC21: 1 | AD21: 2 | AE21: 3944 | AF21: 4306 | AG21: 5 | AH21: 11 | AI21: 3 | AJ21: 3 | AK21: 80 | AL21: 0 | AM21: 6 | AN21: 3 | AO21: 3 | AP21: 2 | AQ21: 1 | AR21: 2
A22: No | B22: Non-Travel | C22: Under 25 | D22: Current Employees | E22: R&D | F22: Other | G22: STAFF-26 | H22: 26 | I22: Female | J22: Manufacturing Director | K22: Divorced | L22: No | M22: Y | N22: 5 | O22: -2 | P22: 0 | Q22: 24 | R22: 0 | T22: 0 | U22: 1 | V22: 673 | W22: 11 | X22: Associates Degree | Y22: 1 | Z22: 1 | AA22: 96 | AB22: 4 | AC22: 2 | AD22: 3 | AE22: 4011 | AF22: 8232 | AG22: 0 | AH22: 18 | AI22: 3 | AJ22: 4 | AK22: 80 | AL22: 1 | AM22: 5 | AN22: 2 | AO22: 4 | AP22: 2 | AQ22: 1 | AR22: 3
A23: Yes | B23: Travel_Rarely | C23: 35 - 44 | D23: Ex-Employees | E23: Sales | F23: Life Sciences | G23: STAFF-27 | H23: 27 | I23: Male | J23: Sales Representative | K23: Single | L23: No | M23: Y | N23: 4 | O23: -2 | P23: 0 | Q23: 36 | R23: 1 | S23: 1 | T23: 1 | U23: 0 | V23: 1218 | W23: 9 | X23: Master's Degree | Y23: 1 | Z23: 3 | AA23: 82 | AB23: 2 | AC23: 1 | AD23: 2 | AE23: 3407 | AF23: 6986 | AG23: 7 | AH23: 23 | AI23: 4 | AJ23: 2 | AK23: 80 | AL23: 0 | AM23: 10 | AN23: 3 | AO23: 5 | AP23: 3 | AQ23: 0 | AR23: 3
A24: No | B24: Travel_Rarely | C24: 25 - 34 | D24: Current Employees | E24: R&D | F24: Life Sciences | G24: STAFF-28 | H24: 28 | I24: Female | J24: Research Director | K24: Single | L24: No | M24: Y | N24: 4 | O24: -2 | P24: 0 | Q24: 34 | R24: 0 | T24: 0 | U24: 1 | V24: 419 | W24: 7 | X24: Master's Degree | Y24: 1 | Z24: 1 | AA24: 53 | AB24: 3 | AC24: 3 | AD24: 2 | AE24: 11994 | AF24: 21293 | AG24: 0 | AH24: 11 | AI24: 3 | AJ24: 3 | AK24: 80 | AL24: 0 | AM24: 13 | AN24: 3 | AO24: 12 | AP24: 6 | AQ24: 2 | AR24: 11
A25: No | B25: Travel_Rarely | C25: Under 25 | D25: Current Employees | E25: R&D | F25: Life Sciences | G25: STAFF-30 | H25: 30 | I25: Male | J25: Research Scientist | K25: Single | L25: No | M25: Y | N25: 6 | O25: -2 | P25: 0 | Q25: 21 | R25: 0 | T25: 0 | U25: 1 | V25: 391 | W25: 15 | X25: Associates Degree | Y25: 1 | Z25: 3 | AA25: 96 | AB25: 3 | AC25: 1 | AD25: 2 | AE25: 1232 | AF25: 19281 | AG25: 1 | AH25: 14 | AI25: 3 | AJ25: 4 | AK25: 80 | AL25: 0 | AM25: 0 | AN25: 3 | AO25: 0 | AP25: 0 | AQ25: 0 | AR25: 0
A26: Yes | B26: Travel_Rarely | C26: 25 - 34 | D26: Ex-Employees | E26: R&D | F26: Medical | G26: STAFF-31 | H26: 31 | I26: Male | J26: Research Scientist | K26: Single | L26: No | M26: Y | N26: 2 | O26: -2 | P26: 0 | Q26: 34 | R26: 1 | S26: 1 | T26: 1 | U26: 0 | V26: 699 | W26: 6 | X26: High School | Y26: 1 | Z26: 2 | AA26: 83 | AB26: 3 | AC26: 1 | AD26: 4 | AE26: 2960 | AF26: 17102 | AG26: 2 | AH26: 11 | AI26: 3 | AJ26: 3 | AK26: 80 | AL26: 0 | AM26: 8 | AN26: 3 | AO26: 4 | AP26: 2 | AQ26: 1 | AR26: 3
A27: No | B27: Travel_Rarely | C27: 45 - 54 | D27: Current Employees | E27: R&D | F27: Other | G27: STAFF-32 | H27: 32 | I27: Female | J27: Manager | K27: Divorced | L27: No | M27: Y | N27: 3 | O27: -2 | P27: 0 | Q27: 53 | R27: 0 | T27: 0 | U27: 1 | V27: 1282 | W27: 5 | X27: Bachelor's Degree | Y27: 1 | Z27: 3 | AA27: 58 | AB27: 3 | AC27: 5 | AD27: 3 | AE27: 19094 | AF27: 10735 | AG27: 4 | AH27: 11 | AI27: 3 | AJ27: 4 | AK27: 80 | AL27: 1 | AM27: 26 | AN27: 2 | AO27: 14 | AP27: 13 | AQ27: 4 | AR27: 8
A28: Yes | B28: Travel_Frequently | C28: 25 - 34 | D28: Ex-Employees | E28: R&D | F28: Life Sciences | G28: STAFF-33 | H28: 33 | I28: Female | J28: Research Scientist | K28: Single | L28: Yes | M28: Y | N28: 5 | O28: -2 | P28: 0 | Q28: 32 | R28: 1 | S28: 1 | T28: 1 | U28: 0 | V28: 1125 | W28: 16 | X28: High School | Y28: 1 | Z28: 2 | AA28: 72 | AB28: 1 | AC28: 1 | AD28: 2 | AE28: 3919 | AF28: 4681 | AG28: 1 | AH28: 22 | AI28: 4 | AJ28: 2 | AK28: 80 | AL28: 0 | AM28: 10 | AN28: 3 | AO28: 10 | AP28: 2 | AQ28: 6 | AR28: 7
A29: No | B29: Travel_Rarely | C29: 35 - 44 | D29: Current Employees | E29: Sales | F29: Marketing | G29: STAFF-35 | H29: 35 | I29: Male | J29: Sales Executive | K29: Married | L29: No | M29: Y | N29: 2 | O29: -2 | P29: 0 | Q29: 42 | R29: 0 | T29: 0 | U29: 1 | V29: 691 | W29: 8 | X29: Master's Degree | Y29: 1 | Z29: 3 | AA29: 48 | AB29: 3 | AC29: 2 | AD29: 3 | AE29: 6825 | AF29: 21173 | AG29: 0 | AH29: 11 | AI29: 3 | AJ29: 4 | AK29: 80 | AL29: 1 | AM29: 10 | AN29: 3 | AO29: 9 | AP29: 7 | AQ29: 4 | AR29: 2
A30: No | B30: Travel_Rarely | C30: 35 - 44 | D30: Current Employees | E30: R&D | F30: Medical | G30: STAFF-36 | H30: 36 | I30: Female | J30: Healthcare Representative | K30: Married | L30: No | M30: Y | N30: 4 | O30: -2 | P30: 0 | Q30: 44 | R30: 0 | T30: 0 | U30: 1 | V30: 477 | W30: 7 | X30: Master's Degree | Y30: 1 | Z30: 1 | AA30: 42 | AB30: 2 | AC30: 3 | AD30: 4 | AE30: 10248 | AF30: 2094 | AG30: 3 | AH30: 14 | AI30: 3 | AJ30: 4 | AK30: 80 | AL30: 1 | AM30: 24 | AN30: 3 | AO30: 22 | AP30: 6 | AQ30: 5 | AR30: 17
A31: No | B31: Travel_Rarely | C31: 45 - 54 | D31: Current Employees | E31: Sales | F31: Marketing | G31: STAFF-38 | H31: 38 | I31: Female | J31: Manager | K31: Single | L31: No | M31: Y | N31: 2 | O31: -2 | P31: 0 | Q31: 46 | R31: 0 | T31: 0 | U31: 1 | V31: 705 | W31: 2 | X31: Master's Degree | Y31: 1 | Z31: 2 | AA31: 83 | AB31: 3 | AC31: 5 | AD31: 4 | AE31: 18947 | AF31: 22822 | AG31: 3 | AH31: 12 | AI31: 3 | AJ31: 4 | AK31: 80 | AL31: 0 | AM31: 22 | AN31: 2 | AO31: 2 | AP31: 2 | AQ31: 2 | AR31: 1
A32: No | B32: Travel_Rarely | C32: 25 - 34 | D32: Current Employees | E32: R&D | F32: Medical | G32: STAFF-39 | H32: 39 | I32: Male | J32: Laboratory Technician | K32: Single | L32: No | M32: Y | N32: 3 | O32: -2 | P32: 0 | Q32: 33 | R32: 0 | T32: 0 | U32: 1 | V32: 924 | W32: 2 | X32: Bachelor's Degree | Y32: 1 | Z32: 3 | AA32: 78 | AB32: 3 | AC32: 1 | AD32: 4 | AE32: 2496 | AF32: 6670 | AG32: 4 | AH32: 11 | AI32: 3 | AJ32: 4 | AK32: 80 | AL32: 0 | AM32: 7 | AN32: 3 | AO32: 1 | AP32: 1 | AQ32: 0 | AR32: 0
A33: No | B33: Travel_Rarely | C33: 35 - 44 | D33: Current Employees | E33: R&D | F33: Other | G33: STAFF-40 | H33: 40 | I33: Male | J33: Healthcare Representative | K33: Married | L33: Yes | M33: Y | N33: 5 | O33: -2 | P33: 0 | Q33: 44 | R33: 0 | T33: 0 | U33: 1 | V33: 1459 | W33: 10 | X33: Master's Degree | Y33: 1 | Z33: 4 | AA33: 41 | AB33: 3 | AC33: 2 | AD33: 4 | AE33: 6465 | AF33: 19121 | AG33: 2 | AH33: 13 | AI33: 3 | AJ33: 4 | AK33: 80 | AL33: 0 | AM33: 9 | AN33: 4 | AO33: 4 | AP33: 2 | AQ33: 1 | AR33: 3
A34: No | B34: Travel_Rarely | C34: 25 - 34 | D34: Current Employees | E34: R&D | F34: Medical | G34: STAFF-41 | H34: 41 | I34: Male | J34: Laboratory Technician | K34: Single | L34: No | M34: Y | N34: 5 | O34: -2 | P34: 0 | Q34: 30 | R34: 0 | T34: 0 | U34: 1 | V34: 125 | W34: 9 | X34: Associates Degree | Y34: 1 | Z34: 4 | AA34: 83 | AB34: 2 | AC34: 1 | AD34: 3 | AE34: 2206 | AF34: 16117 | AG34: 1 | AH34: 13 | AI34: 3 | AJ34: 1 | AK34: 80 | AL34: 0 | AM34: 10 | AN34: 3 | AO34: 10 | AP34: 0 | AQ34: 1 | AR34: 8
A35: Yes | B35: Travel_Rarely | C35: 35 - 44 | D35: Ex-Employees | E35: Sales | F35: Technical Degree | G35: STAFF-42 | H35: 42 | I35: Male | J35: Sales Representative | K35: Married | L35: No | M35: Y | N35: 6 | O35: -2 | P35: 0 | Q35: 39 | R35: 1 | S35: 1 | T35: 1 | U35: 0 | V35: 895 | W35: 5 | X35: Bachelor's Degree | Y35: 1 | Z35: 4 | AA35: 56 | AB35: 3 | AC35: 2 | AD35: 4 | AE35: 2086 | AF35: 3335 | AG35: 3 | AH35: 14 | AI35: 3 | AJ35: 3 | AK35: 80 | AL35: 1 | AM35: 19 | AN35: 4 | AO35: 1 | AP35: 0 | AQ35: 0 | AR35: 0
A36: Yes | B36: Travel_Rarely | C36: Under 25 | D36: Ex-Employees | E36: R&D | F36: Medical | G36: STAFF-45 | H36: 45 | I36: Male | J36: Research Scientist | K36: Married | L36: Yes | M36: Y | N36: 2 | O36: -2 | P36: 0 | Q36: 24 | R36: 1 | S36: 1 | T36: 1 | U36: 0 | V36: 813 | W36: 1 | X36: Bachelor's Degree | Y36: 1 | Z36: 2 | AA36: 61 | AB36: 3 | AC36: 1 | AD36: 4 | AE36: 2293 | AF36: 3020 | AG36: 2 | AH36: 16 | AI36: 3 | AJ36: 1 | AK36: 80 | AL36: 1 | AM36: 6 | AN36: 2 | AO36: 2 | AP36: 0 | AQ36: 2 | AR36: 0
A37: No | B37: Travel_Rarely | C37: 35 - 44 | D37: Current Employees | E37: R&D | F37: Medical | G37: STAFF-46 | H37: 46 | I37: Female | J37: Research Scientist | K37: Divorced | L37: No | M37: Y | N37: 3 | O37: -2 | P37: 0 | Q37: 43 | R37: 0 | T37: 0 | U37: 1 | V37: 1273 | W37: 2 | X37: Associates Degree | Y37: 1 | Z37: 4 | AA37: 72 | AB37: 4 | AC37: 1 | AD37: 3 | AE37: 2645 | AF37: 21923 | AG37: 1 | AH37: 12 | AI37: 3 | AJ37: 4 | AK37: 80 | AL37: 2 | AM37: 6 | AN37: 2 | AO37: 5 | AP37: 3 | AQ37: 1 | AR37: 4
A38: Yes | B38: Travel_Rarely | C38: 45 - 54 | D38: Ex-Employees | E38: Sales | F38: Marketing | G38: STAFF-47 | H38: 47 | I38: Male | J38: Sales Representative | K38: Married | L38: Yes | M38: Y | N38: 2 | O38: -2 | P38: 0 | Q38: 50 | R38: 1 | S38: 1 | T38: 1 | U38: 0 | V38: 869 | W38: 3 | X38: Associates Degree | Y38: 1 | Z38: 1 | AA38: 86 | AB38: 2 | AC38: 1 | AD38: 3 | AE38: 2683 | AF38: 3810 | AG38: 1 | AH38: 14 | AI38: 3 | AJ38: 3 | AK38: 80 | AL38: 0 | AM38: 3 | AN38: 3 | AO38: 3 | AP38: 2 | AQ38: 0 | AR38: 2
A39: No | B39: Travel_Rarely | C39: 35 - 44 | D39: Current Employees | E39: Sales | F39: Marketing | G39: STAFF-49 | H39: 49 | I39: Female | J39: Sales Representative | K39: Married | L39: No | M39: Y | N39: 3 | O39: -2 | P39: 0 | Q39: 35 | R39: 0 | T39: 0 | U39: 1 | V39: 890 | W39: 2 | X39: Bachelor's Degree | Y39: 1 | Z39: 4 | AA39: 97 | AB39: 3 | AC39: 1 | AD39: 4 | AE39: 2014 | AF39: 9687 | AG39: 1 | AH39: 13 | AI39: 3 | AJ39: 1 | AK39: 80 | AL39: 0 | AM39: 2 | AN39: 3 | AO39: 2 | AP39: 2 | AQ39: 2 | AR39: 2
A40: No | B40: Travel_Rarely | C40: 35 - 44 | D40: Current Employees | E40: R&D | F40: Life Sciences | G40: STAFF-51 | H40: 51 | I40: Female | J40: Research Scientist | K40: Married | L40: Yes | M40: Y | N40: 3 | O40: -2 | P40: 0 | Q40: 36 | R40: 0 | T40: 0 | U40: 1 | V40: 852 | W40: 5 | X40: Master's Degree | Y40: 1 | Z40: 2 | AA40: 82 | AB40: 2 | AC40: 1 | AD40: 2 | AE40: 3419 | AF40: 13072 | AG40: 9 | AH40: 14 | AI40: 3 | AJ40: 4 | AK40: 80 | AL40: 1 | AM40: 6 | AN40: 4 | AO40: 1 | AP40: 1 | AQ40: 0 | AR40: 0
A41: No | B41: Travel_Frequently | C41: 25 - 34 | D41: Current Employees | E41: Sales | F41: Life Sciences | G41: STAFF-52 | H41: 52 | I41: Female | J41: Sales Executive | K41: Married | L41: No | M41: Y | N41: 3 | O41: -2 | P41: 0 | Q41: 33 | R41: 0 | T41: 0 | U41: 1 | V41: 1141 | W41: 1 | X41: Bachelor's Degree | Y41: 1 | Z41: 3 | AA41: 42 | AB41: 4 | AC41: 2 | AD41: 2 | AE41: 5376 | AF41: 3193 | AG41: 2 | AH41: 19 | AI41: 3 | AJ41: 1 | AK41: 80 | AL41: 2 | AM41: 10 | AN41: 3 | AO41: 5 | AP41: 3 | AQ41: 1 | AR41: 3
A42: No | B42: Travel_Rarely | C42: 35 - 44 | D42: Current Employees | E42: R&D | F42: Other | G42: STAFF-53 | H42: 53 | I42: Male | J42: Laboratory Technician | K42: Divorced | L42: No | M42: Y | N42: 3 | O42: -2 | P42: 0 | Q42: 35 | R42: 0 | T42: 0 | U42: 1 | V42: 464 | W42: 4 | X42: Associates Degree | Y42: 1 | Z42: 3 | AA42: 75 | AB42: 3 | AC42: 1 | AD42: 4 | AE42: 1951 | AF42: 10910 | AG42: 1 | AH42: 12 | AI42: 3 | AJ42: 3 | AK42: 80 | AL42: 1 | AM42: 1 | AN42: 3 | AO42: 1 | AP42: 0 | AQ42: 0 | AR42: 0
A43: No | B43: Travel_Rarely | C43: 25 - 34 | D43: Current Employees | E43: R&D | F43: Life Sciences | G43: STAFF-54 | H43: 54 | I43: Female | J43: Laboratory Technician | K43: Divorced | L43: No | M43: Y | N43: 6 | O43: -2 | P43: 0 | Q43: 27 | R43: 0 | T43: 0 | U43: 1 | V43: 1240 | W43: 2 | X43: Master's Degree | Y43: 1 | Z43: 4 | AA43: 33 | AB43: 3 | AC43: 1 | AD43: 2 | AE43: 2341 | AF43: 19715 | AG43: 1 | AH43: 13 | AI43: 3 | AJ43: 4 | AK43: 80 | AL43: 1 | AM43: 1 | AN43: 3 | AO43: 1 | AP43: 0 | AQ43: 0 | AR43: 0
A44: Yes | B44: Travel_Rarely | C44: 25 - 34 | D44: Ex-Employees | E44: R&D | F44: Life Sciences | G44: STAFF-55 | H44: 55 | I44: Male | J44: Laboratory Technician | K44: Single | L44: No | M44: Y | N44: 2 | O44: -2 | P44: 0 | Q44: 26 | R44: 1 | S44: 1 | T44: 1 | U44: 0 | V44: 1357 | W44: 25 | X44: Bachelor's Degree | Y44: 1 | Z44: 1 | AA44: 48 | AB44: 1 | AC44: 1 | AD44: 2 | AE44: 2293 | AF44: 10558 | AG44: 1 | AH44: 12 | AI44: 3 | AJ44: 3 | AK44: 80 | AL44: 0 | AM44: 1 | AN44: 2 | AO44: 1 | AP44: 0 | AQ44: 0 | AR44: 1
A45: No | B45: Travel_Frequently | C45: 25 - 34 | D45: Current Employees | E45: Sales | F45: Life Sciences | G45: STAFF-56 | H45: 56 | I45: Male | J45: Sales Executive | K45: Single | L45: No | M45: Y | N45: 0 | O45: -2 | P45: 0 | Q45: 27 | R45: 0 | T45: 0 | U45: 1 | V45: 994 | W45: 8 | X45: Bachelor's Degree | Y45: 1 | Z45: 4 | AA45: 37 | AB45: 3 | AC45: 3 | AD45: 2 | AE45: 8726 | AF45: 2975 | AG45: 1 | AH45: 15 | AI45: 3 | AJ45: 4 | AK45: 80 | AL45: 0 | AM45: 9 | AN45: 3 | AO45: 9 | AP45: 8 | AQ45: 1 | AR45: 7
A46: No | B46: Travel_Frequently | C46: 25 - 34 | D46: Current Employees | E46: R&D | F46: Medical | G46: STAFF-57 | H46: 57 | I46: Female | J46: Laboratory Technician | K46: Single | L46: No | M46: Y | N46: 2 | O46: -2 | P46: 0 | Q46: 30 | R46: 0 | T46: 0 | U46: 1 | V46: 721 | W46: 1 | X46: Associates Degree | Y46: 1 | Z46: 3 | AA46: 58 | AB46: 3 | AC46: 2 | AD46: 4 | AE46: 4011 | AF46: 10781 | AG46: 1 | AH46: 23 | AI46: 4 | AJ46: 4 | AK46: 80 | AL46: 0 | AM46: 12 | AN46: 3 | AO46: 12 | AP46: 8 | AQ46: 3 | AR46: 7
A47: Yes | B47: Travel_Rarely | C47: 35 - 44 | D47: Ex-Employees | E47: R&D | F47: Technical Degree | G47: STAFF-58 | H47: 58 | I47: Female | J47: Research Director | K47: Married | L47: No | M47: Y | N47: 0 | O47: -2 | P47: 0 | Q47: 41 | R47: 1 | S47: 1 | T47: 1 | U47: 0 | V47: 1360 | W47: 12 | X47: Bachelor's Degree | Y47: 1 | Z47: 2 | AA47: 49 | AB47: 3 | AC47: 5 | AD47: 3 | AE47: 19545 | AF47: 16280 | AG47: 1 | AH47: 12 | AI47: 3 | AJ47: 4 | AK47: 80 | AL47: 0 | AM47: 23 | AN47: 3 | AO47: 22 | AP47: 15 | AQ47: 15 | AR47: 8
A48: No | B48: Non-Travel | C48: 25 - 34 | D48: Current Employees | E48: Sales | F48: Marketing | G48: STAFF-60 | H48: 60 | I48: Male | J48: Sales Executive | K48: Single | L48: No | M48: Y | N48: 2 | O48: -2 | P48: 0 | Q48: 34 | R48: 0 | T48: 0 | U48: 1 | V48: 1065 | W48: 23 | X48: Master's Degree | Y48: 1 | Z48: 2 | AA48: 72 | AB48: 3 | AC48: 2 | AD48: 3 | AE48: 4568 | AF48: 10034 | AG48: 0 | AH48: 20 | AI48: 4 | AJ48: 3 | AK48: 80 | AL48: 0 | AM48: 10 | AN48: 3 | AO48: 9 | AP48: 5 | AQ48: 8 | AR48: 7
A49: No | B49: Travel_Rarely | C49: 35 - 44 | D49: Current Employees | E49: R&D | F49: Life Sciences | G49: STAFF-61 | H49: 61 | I49: Male | J49: Research Scientist | K49: Married | L49: No | M49: Y | N49: 1 | O49: -2 | P49: 0 | Q49: 37 | R49: 0 | T49: 0 | U49: 1 | V49: 408 | W49: 19 | X49: Associates Degree | Y49: 1 | Z49: 2 | AA49: 73 | AB49: 3 | AC49: 1 | AD49: 2 | AE49: 3022 | AF49: 10227 | AG49: 4 | AH49: 21 | AI49: 4 | AJ49: 1 | AK49: 80 | AL49: 0 | AM49: 8 | AN49: 3 | AO49: 1 | AP49: 0 | AQ49: 0 | AR49: 0
A50: No | B50: Travel_Frequently | C50: 45 - 54 | D50: Current Employees | E50: Sales | F50: Marketing | G50: STAFF-62 | H50: 62 | I50: Male | J50: Sales Executive | K50: Single | L50: Yes | M50: Y | N50: 4 | O50: -2 | P50: 0 | Q50: 46 | R50: 0 | T50: 0 | U50: 1 | V50: 1211 | W50: 5 | X50: Master's Degree | Y50: 1 | Z50: 1 | AA50: 98 | AB50: 3 | AC50: 2 | AD50: 4 | AE50: 5772 | AF50: 20445 | AG50: 4 | AH50: 21 | AI50: 4 | AJ50: 3 | AK50: 80 | AL50: 0 | AM50: 14 | AN50: 3 | AO50: 9 | AP50: 6 | AQ50: 0 | AR50: 8
A51: No | B51: Travel_Rarely | C51: 35 - 44 | D51: Current Employees | E51: R&D | F51: Life Sciences | G51: STAFF-63 | H51: 63 | I51: Male | J51: Laboratory Technician | K51: Married | L51: No | M51: Y | N51: 2 | O51: -2 | P51: 0 | Q51: 35 | R51: 0 | T51: 0 | U51: 1 | V51: 1229 | W51: 8 | X51: High School | Y51: 1 | Z51: 4 | AA51: 36 | AB51: 4 | AC51: 1 | AD51: 2 | AE51: 2269 | AF51: 4892 | AG51: 1 | AH51: 19 | AI51: 3 | AJ51: 4 | AK51: 80 | AL51: 0 | AM51: 1 | AN51: 3 | AO51: 1 | AP51: 0 | AQ51: 0 | AR51: 1
A52: Yes | B52: Travel_Rarely | C52: 45 - 54 | D52: Ex-Employees | E52: R&D | F52: Life Sciences | G52: STAFF-64 | H52: 64 | I52: Male | J52: Laboratory Technician | K52: Single | L52: Yes | M52: Y | N52: 2 | O52: -2 | P52: 0 | Q52: 48 | R52: 1 | S52: 1 | T52: 1 | U52: 0 | V52: 626 | W52: 1 | X52: Associates Degree | Y52: 1 | Z52: 1 | AA52: 98 | AB52: 2 | AC52: 3 | AD52: 2 | AE52: 5381 | AF52: 19294 | AG52: 9 | AH52: 13 | AI52: 3 | AJ52: 4 | AK52: 80 | AL52: 0 | AM52: 23 | AN52: 3 | AO52: 1 | AP52: 0 | AQ52: 0 | AR52: 0
A53: Yes | B53: Travel_Rarely | C53: 25 - 34 | D53: Ex-Employees | E53: R&D | F53: Technical Degree | G53: STAFF-65 | H53: 65 | I53: Male | J53: Laboratory Technician | K53: Single | L53: Yes | M53: Y | N53: 3 | O53: -2 | P53: 0 | Q53: 28 | R53: 1 | S53: 1 | T53: 1 | U53: 0 | V53: 1434 | W53: 5 | X53: Master's Degree | Y53: 1 | Z53: 3 | AA53: 50 | AB53: 3 | AC53: 1 | AD53: 3 | AE53: 3441 | AF53: 11179 | AG53: 1 | AH53: 13 | AI53: 3 | AJ53: 3 | AK53: 80 | AL53: 0 | AM53: 2 | AN53: 2 | AO53: 2 | AP53: 2 | AQ53: 2 | AR53: 2
A54: No | B54: Travel_Rarely | C54: 35 - 44 | D54: Current Employees | E54: Sales | F54: Marketing | G54: STAFF-68 | H54: 68 | I54: Female | J54: Sales Executive | K54: Divorced | L54: Yes | M54: Y | N54: 2 | O54: -2 | P54: 0 | Q54: 44 | R54: 0 | T54: 0 | U54: 1 | V54: 1488 | W54: 1 | X54: Doctoral Degree | Y54: 1 | Z54: 2 | AA54: 75 | AB54: 3 | AC54: 2 | AD54: 4 | AE54: 5454 | AF54: 4009 | AG54: 5 | AH54: 21 | AI54: 4 | AJ54: 3 | AK54: 80 | AL54: 1 | AM54: 9 | AN54: 2 | AO54: 4 | AP54: 3 | AQ54: 1 | AR54: 3
A55: No | B55: Non-Travel | C55: 35 - 44 | D55: Current Employees | E55: R&D | F55: Medical | G55: STAFF-70 | H55: 70 | I55: Male | J55: Healthcare Representative | K55: Married | L55: Yes | M55: Y | N55: 3 | O55: -2 | P55: 0 | Q55: 35 | R55: 0 | T55: 0 | U55: 1 | V55: 1097 | W55: 11 | X55: Associates Degree | Y55: 1 | Z55: 3 | AA55: 79 | AB55: 2 | AC55: 3 | AD55: 4 | AE55: 9884 | AF55: 8302 | AG55: 2 | AH55: 13 | AI55: 3 | AJ55: 3 | AK55: 80 | AL55: 1 | AM55: 10 | AN55: 3 | AO55: 4 | AP55: 0 | AQ55: 2 | AR55: 3
A56: No | B56: Travel_Rarely | C56: 25 - 34 | D56: Current Employees | E56: Sales | F56: Marketing | G56: STAFF-72 | H56: 72 | I56: Female | J56: Sales Executive | K56: Married | L56: Yes | M56: Y | N56: 2 | O56: -2 | P56: 0 | Q56: 26 | R56: 0 | T56: 0 | U56: 1 | V56: 1443 | W56: 23 | X56: Bachelor's Degree | Y56: 1 | Z56: 3 | AA56: 47 | AB56: 2 | AC56: 2 | AD56: 4 | AE56: 4157 | AF56: 21436 | AG56: 7 | AH56: 19 | AI56: 3 | AJ56: 3 | AK56: 80 | AL56: 1 | AM56: 5 | AN56: 2 | AO56: 2 | AP56: 2 | AQ56: 0 | AR56: 0
A57: No | B57: Travel_Frequently | C57: 25 - 34 | D57: Current Employees | E57: R&D | F57: Life Sciences | G57: STAFF-73 | H57: 73 | I57: Female | J57: Research Director | K57: Single | L57: Yes | M57: Y | N57: 1 | O57: -2 | P57: 0 | Q57: 33 | R57: 0 | T57: 0 | U57: 1 | V57: 515 | W57: 1 | X57: Associates Degree | Y57: 1 | Z57: 1 | AA57: 98 | AB57: 3 | AC57: 3 | AD57: 2 | AE57: 13458 | AF57: 15146 | AG57: 1 | AH57: 12 | AI57: 3 | AJ57: 3 | AK57: 80 | AL57: 0 | AM57: 15 | AN57: 3 | AO57: 15 | AP57: 14 | AQ57: 8 | AR57: 12
A58: No | B58: Travel_Frequently | C58: 35 - 44 | D58: Current Employees | E58: Sales | F58: Life Sciences | G58: STAFF-74 | H58: 74 | I58: Male | J58: Sales Executive | K58: Married | L58: No | M58: Y | N58: 3 | O58: -2 | P58: 0 | Q58: 35 | R58: 0 | T58: 0 | U58: 1 | V58: 853 | W58: 18 | X58: Doctoral Degree | Y58: 1 | Z58: 2 | AA58: 71 | AB58: 3 | AC58: 3 | AD58: 2 | AE58: 9069 | AF58: 11031 | AG58: 1 | AH58: 22 | AI58: 4 | AJ58: 4 | AK58: 80 | AL58: 1 | AM58: 9 | AN58: 2 | AO58: 9 | AP58: 8 | AQ58: 1 | AR58: 8
A59: No | B59: Travel_Rarely | C59: 35 - 44 | D59: Current Employees | E59: R&D | F59: Medical | G59: STAFF-75 | H59: 75 | I59: Female | J59: Laboratory Technician | K59: Married | L59: Yes | M59: Y | N59: 3 | O59: -2 | P59: 0 | Q59: 35 | R59: 0 | T59: 0 | U59: 1 | V59: 1142 | W59: 23 | X59: Master's Degree | Y59: 1 | Z59: 3 | AA59: 30 | AB59: 3 | AC59: 1 | AD59: 4 | AE59: 4014 | AF59: 16002 | AG59: 3 | AH59: 15 | AI59: 3 | AJ59: 3 | AK59: 80 | AL59: 1 | AM59: 4 | AN59: 3 | AO59: 2 | AP59: 2 | AQ59: 2 | AR59: 2
A60: No | B60: Travel_Rarely | C60: 25 - 34 | D60: Current Employees | E60: R&D | F60: Life Sciences | G60: STAFF-76 | H60: 76 | I60: Male | J60: Laboratory Technician | K60: Divorced | L60: No | M60: Y | N60: 3 | O60: -2 | P60: 0 | Q60: 31 | R60: 0 | T60: 0 | U60: 1 | V60: 655 | W60: 7 | X60: Master's Degree | Y60: 1 | Z60: 4 | AA60: 48 | AB60: 3 | AC60: 2 | AD60: 2 | AE60: 5915 | AF60: 9528 | AG60: 3 | AH60: 22 | AI60: 4 | AJ60: 4 | AK60: 80 | AL60: 1 | AM60: 10 | AN60: 2 | AO60: 7 | AP60: 7 | AQ60: 1 | AR60: 7
A61: No | B61: Travel_Rarely | C61: 35 - 44 | D61: Current Employees | E61: R&D | F61: Life Sciences | G61: STAFF-77 | H61: 77 | I61: Male | J61: Manufacturing Director | K61: Divorced | L61: No | M61: Y | N61: 2 | O61: -2 | P61: 0 | Q61: 37 | R61: 0 | T61: 0 | U61: 1 | V61: 1115 | W61: 1 | X61: Master's Degree | Y61: 1 | Z61: 1 | AA61: 51 | AB61: 2 | AC61: 2 | AD61: 2 | AE61: 5993 | AF61: 2689 | AG61: 1 | AH61: 18 | AI61: 3 | AJ61: 3 | AK61: 80 | AL61: 1 | AM61: 7 | AN61: 4 | AO61: 7 | AP61: 5 | AQ61: 0 | AR61: 7
A62: No | B62: Travel_Rarely | C62: 25 - 34 | D62: Current Employees | E62: R&D | F62: Medical | G62: STAFF-78 | H62: 78 | I62: Male | J62: Manufacturing Director | K62: Married | L62: Yes | M62: Y | N62: 3 | O62: -2 | P62: 0 | Q62: 32 | R62: 0 | T62: 0 | U62: 1 | V62: 427 | W62: 1 | X62: Bachelor's Degree | Y62: 1 | Z62: 1 | AA62: 33 | AB62: 3 | AC62: 2 | AD62: 4 | AE62: 6162 | AF62: 10877 | AG62: 1 | AH62: 22 | AI62: 4 | AJ62: 2 | AK62: 80 | AL62: 1 | AM62: 9 | AN62: 3 | AO62: 9 | AP62: 8 | AQ62: 7 | AR62: 8
A63: No | B63: Travel_Frequently | C63: 35 - 44 | D63: Current Employees | E63: R&D | F63: Life Sciences | G63: STAFF-79 | H63: 79 | I63: Female | J63: Laboratory Technician | K63: Single | L63: No | M63: Y | N63: 2 | O63: -2 | P63: 0 | Q63: 38 | R63: 0 | T63: 0 | U63: 1 | V63: 653 | W63: 29 | X63: Doctoral Degree | Y63: 1 | Z63: 4 | AA63: 50 | AB63: 3 | AC63: 2 | AD63: 2 | AE63: 2406 | AF63: 5456 | AG63: 1 | AH63: 11 | AI63: 3 | AJ63: 4 | AK63: 80 | AL63: 0 | AM63: 10 | AN63: 3 | AO63: 10 | AP63: 3 | AQ63: 9 | AR63: 9
A64: No | B64: Travel_Rarely | C64: 45 - 54 | D64: Current Employees | E64: R&D | F64: Medical | G64: STAFF-80 | H64: 80 | I64: Female | J64: Research Director | K64: Divorced | L64: Yes | M64: Y | N64: 2 | O64: -2 | P64: 0 | Q64: 50 | R64: 0 | T64: 0 | U64: 1 | V64: 989 | W64: 7 | X64: Associates Degree | Y64: 1 | Z64: 2 | AA64: 43 | AB64: 2 | AC64: 5 | AD64: 3 | AE64: 18740 | AF64: 16701 | AG64: 5 | AH64: 12 | AI64: 3 | AJ64: 4 | AK64: 80 | AL64: 1 | AM64: 29 | AN64: 2 | AO64: 27 | AP64: 3 | AQ64: 13 | AR64: 8
A65: No | B65: Travel_Rarely | C65: Over 55 | D65: Current Employees | E65: Sales | F65: Life Sciences | G65: STAFF-81 | H65: 81 | I65: Female | J65: Sales Executive | K65: Single | L65: No | M65: Y | N65: 3 | O65: -2 | P65: 0 | Q65: 59 | R65: 0 | T65: 0 | U65: 1 | V65: 1435 | W65: 25 | X65: Bachelor's Degree | Y65: 1 | Z65: 1 | AA65: 99 | AB65: 3 | AC65: 3 | AD65: 2 | AE65: 7637 | AF65: 2354 | AG65: 7 | AH65: 11 | AI65: 3 | AJ65: 4 | AK65: 80 | AL65: 0 | AM65: 28 | AN65: 2 | AO65: 21 | AP65: 16 | AQ65: 7 | AR65: 9
... A70: No | B70: Travel_Frequently | C70: 35 - 44 | D70: Current Employees | E70: R&D | F70: Medical | G70: STAFF-88 | H70: 88 | I70: Male | J70: Research Scientist | K70: Married | L70: No | M70: Y | N70: 2 | O70: -2 | P70: 0 | Q70: 35 | R70: 0 | T70: 0 | U70: 1 | V70: 664 | W70: 1 | X70: Bachelor's Degree | Y70: 1 | Z70: 2 | AA70: 79 | AB70: 3 | AC70: 1 | AD70: 4 | AE70: 2194 | AF70: 5868 | AG70: 4 | AH70: 13 | AI70: 3 | AJ70: 4 | AK70: 80 | AL70: 1 | AM70: 5 | AN70: 2 | AO70: 3 | AP70: 2 | AQ70: 1 | AR70: 2
A71: Yes | B71: Travel_Rarely | C71: 35 - 44 | D71: Ex-Employees | E71: R&D | F71: Medical | G71: STAFF-90 | H71: 90 | I71: Male | J71: Research Scientist | K71: Married | L71: Yes | M71: Y | N71: 0 | O71: -2 | P71: 0 | Q71: 36 | R71: 1 | S71: 1 | T71: 1 | U71: 0 | V71: 318 | W71: 9 | X71: Bachelor's Degree | Y71: 1 | Z71: 4 | AA71: 79 | AB71: 2 | AC71: 1 | AD71: 3 | AE71: 3388 | AF71: 21777 | AG71: 0 | AH71: 17 | AI71: 3 | AJ71: 1 | AK71: 80 | AL71: 1 | AM71: 2 | AN71: 2 | AO71: 1 | AP71: 0 | AQ71: 0 | AR71: 0
A72: No | B72: Travel_Frequently | C72: Over 55 | D72: Current Employees | E72: Sales | F72: Life Sciences | G72: STAFF-91 | H72: 91 | I72: Female | J72: Sales Executive | K72: Single | L72: No | M72: Y | N72: 2 | O72: -2 | P72: 0 | Q72: 59 | R72: 0 | T72: 0 | U72: 1 | V72: 1225 | W72: 1 | X72: High School | Y72: 1 | Z72: 1 | AA72: 57 | AB72: 2 | AC72: 2 | AD72: 2 | AE72: 5473 | AF72: 24668 | AG72: 7 | AH72: 11 | AI72: 3 | AJ72: 4 | AK72: 80 | AL72: 0 | AM72: 20 | AN72: 2 | AO72: 4 | AP72: 3 | AQ72: 1 | AR72: 3
A73: No | B73: Travel_Rarely | C73: 25 - 34 | D73: Current Employees | E73: R&D | F73: Life Sciences | G73: STAFF-94 | H73: 94 | I73: Male | J73: Research Scientist | K73: Married | L73: No | M73: Y | N73: 3 | O73: -2 | P73: 0 | Q73: 29 | R73: 0 | T73: 0 | U73: 1 | V73: 1328 | W73: 2 | X73: Bachelor's Degree | Y73: 1 | Z73: 3 | AA73: 76 | AB73: 3 | AC73: 1 | AD73: 2 | AE73: 2703 | AF73: 4956 | AG73: 0 | AH73: 23 | AI73: 4 | AJ73: 4 | AK73: 80 | AL73: 1 | AM73: 6 | AN73: 3 | AO73: 5 | AP73: 4 | AQ73: 0 | AR73: 4
A74: No | B74: Travel_Rarely | C74: 25 - 34 | D74: Current Employees | E74: R&D | F74: Medical | G74: STAFF-95 | H74: 95 | I74: Male | J74: Research Scientist | K74: Single | L74: No | M74: Y | N74: 4 | O74: -2 | P74: 0 | Q74: 31 | R74: 0 | T74: 0 | U74: 1 | V74: 1082 | W74: 1 | X74: Master's Degree | Y74: 1 | Z74: 3 | AA74: 87 | AB74: 3 | AC74: 1 | AD74: 3 | AE74: 2501 | AF74: 18775 | AG74: 1 | AH74: 17 | AI74: 3 | AJ74: 2 | AK74: 80 | AL74: 0 | AM74: 1 | AN74: 3 | AO74: 1 | AP74: 1 | AQ74: 1 | AR74: 0
A75: No | B75: Travel_Rarely | C75: 25 - 34 | D75: Current Employees | E75: R&D | F75: Life Sciences | G75: STAFF-96 | H75: 96 | I75: Male | J75: Research Scientist | K75: Married | L75: No | M75: Y | N75: 3 | O75: -2 | P75: 0 | Q75: 32 | R75: 0 | T75: 0 | U75: 1 | V75: 548 | W75: 1 | X75: Bachelor's Degree | Y75: 1 | Z75: 2 | AA75: 66 | AB75: 3 | AC75: 2 | AD75: 2 | AE75: 6220 | AF75: 7346 | AG75: 1 | AH75: 17 | AI75: 3 | AJ75: 2 | AK75: 80 | AL75: 2 | AM75: 10 | AN75: 3 | AO75: 10 | AP75: 4 | AQ75: 0 | AR75: 9
A76: No | B76: Travel_Rarely | C76: 35 - 44 | D76: Current Employees | E76: R&D | F76: Life Sciences | G76: STAFF-97 | H76: 97 | I76: Female | J76: Laboratory Technician | K76: Married | L76: No | M76: Y | N76: 3 | O76: -2 | P76: 0 | Q76: 36 | R76: 0 | T76: 0 | U76: 1 | V76: 132 | W76: 6 | X76: Bachelor's Degree | Y76: 1 | Z76: 2 | AA76: 55 | AB76: 4 | AC76: 1 | AD76: 2 | AE76: 3038 | AF76: 22002 | AG76: 3 | AH76: 12 | AI76: 3 | AJ76: 2 | AK76: 80 | AL76: 0 | AM76: 5 | AN76: 3 | AO76: 1 | AP76: 0 | AQ76: 0 | AR76: 0
A77: No | B77: Travel_Rarely | C77: 25 - 34 | D77: Current Employees | E77: R&D | F77: Life Sciences | G77: STAFF-98 | H77: 98 | I77: Female | J77: Manufacturing Director | K77: Single | L77: No | M77: Y | N77: 2 | O77: -2 | P77: 0 | Q77: 31 | R77: 0 | T77: 0 | U77: 1 | V77: 746 | W77: 8 | X77: Master's Degree | Y77: 1 | Z77: 3 | AA77: 61 | AB77: 3 | AC77: 2 | AD77: 2 | AE77: 4424 | AF77: 20682 | AG77: 1 | AH77: 23 | AI77: 4 | AJ77: 4 | AK77: 80 | AL77: 0 | AM77: 11 | AN77: 3 | AO77: 11 | AP77: 7 | AQ77: 1 | AR77: 8
A78: No | B78: Travel_Rarely | C78: 35 - 44 | D78: Current Employees | E78: Sales | F78: Marketing | G78: STAFF-100 | H78: 100 | I78: Male | J78: Sales Executive | K78: Single | L78: No | M78: Y | N78: 2 | O78: -2 | P78: 0 | Q78: 35 | R78: 0 | T78: 0 | U78: 1 | V78: 776 | W78: 1 | X78: Master's Degree | Y78: 1 | Z78: 3 | AA78: 32 | AB78: 2 | AC78: 2 | AD78: 4 | AE78: 4312 | AF78: 23016 | AG78: 0 | AH78: 14 | AI78: 3 | AJ78: 2 | AK78: 80 | AL78: 0 | AM78: 16 | AN78: 3 | AO78: 15 | AP78: 13 | AQ78: 2 | AR78: 8
A79: No | B79: Travel_Rarely | C79: 45 - 54 | D79: Current Employees | E79: R&D | F79: Other | G79: STAFF-101 | H79: 101 | I79: Male | J79: Research Director | K79: Married | L79: Yes | M79: Y | N79: 3 | O79: -2 | P79: 0 | Q79: 45 | R79: 0 | T79: 0 | U79: 1 | V79: 193 | W79: 6 | X79: Master's Degree | Y79: 1 | Z79: 4 | AA79: 52 | AB79: 3 | AC79: 3 | AD79: 4 | AE79: 13245 | AF79: 15067 | AG79: 4 | AH79: 14 | AI79: 3 | AJ79: 2 | AK79: 80 | AL79: 0 | AM79: 17 | AN79: 4 | AO79: 0 | AP79: 0 | AQ79: 0 | AR79: 0
A80: No | B80: Travel_Rarely | C80: 35 - 44 | D80: Current Employees | E80: R&D | F80: Medical | G80: STAFF-102 | H80: 102 | I80: Male | J80: Research Director | K80: Single | L80: No | M80: Y | N80: 3 | O80: -2 | P80: 0 | Q80: 37 | R80: 0 | T80: 0 | U80: 1 | V80: 397 | W80: 7 | X80: Master's Degree | Y80: 1 | Z80: 1 | AA80: 30 | AB80: 3 | AC80: 3 | AD80: 3 | AE80: 13664 | AF80: 25258 | AG80: 4 | AH80: 13 | AI80: 3 | AJ80: 1 | AK80: 80 | AL80: 0 | AM80: 16 | AN80: 4 | AO80: 5 | AP80: 2 | AQ80: 0 | AR80: 2
A81: No | B81: Travel_Rarely | C81: 45 - 54 | D81: Current Employees | E81: HR | F81: Medical | G81: STAFF-103 | H81: 103 | I81: Male | J81: Human Resources | K81: Divorced | L81: Yes | M81: Y | N81: 2 | O81: -2 | P81: 0 | Q81: 46 | R81: 0 | T81: 0 | U81: 1 | V81: 945 | W81: 5 | X81: Associates Degree | Y81: 1 | Z81: 2 | AA81: 80 | AB81: 3 | AC81: 2 | AD81: 3 | AE81: 5021 | AF81: 10425 | AG81: 8 | AH81: 22 | AI81: 4 | AJ81: 4 | AK81: 80 | AL81: 1 | AM81: 16 | AN81: 3 | AO81: 4 | AP81: 2 | AQ81: 0 | AR81: 2
A82: No | B82: Travel_Rarely | C82: 25 - 34 | D82: Current Employees | E82: R&D | F82: Life Sciences | G82: STAFF-104 | H82: 104 | I82: Male | J82: Laboratory Technician | K82: Married | L82: Yes | M82: Y | N82: 1 | O82: -2 | P82: 0 | Q82: 30 | R82: 0 | T82: 0 | U82: 1 | V82: 852 | W82: 1 | X82: High School | Y82: 1 | Z82: 4 | AA82: 55 | AB82: 2 | AC82: 2 | AD82: 2 | AE82: 5126 | AF82: 15998 | AG82: 1 | AH82: 12 | AI82: 3 | AJ82: 3 | AK82: 80 | AL82: 2 | AM82: 10 | AN82: 2 | AO82: 10 | AP82: 8 | AQ82: 3 | AR82: 0
A83: No | B83: Travel_Rarely | C83: 35 - 44 | D83: Current Employees | E83: R&D | F83: Medical | G83: STAFF-105 | H83: 105 | I83: Male | J83: Research Scientist | K83: Single | L83: No | M83: Y | N83: 3 | O83: -2 | P83: 0 | Q83: 35 | R83: 0 | T83: 0 | U83: 1 | V83: 1214 | W83: 1 | X83: Bachelor's Degree | Y83: 1 | Z83: 2 | AA83: 30 | AB83: 2 | AC83: 1 | AD83: 3 | AE83: 2859 | AF83: 26278 | AG83: 1 | AH83: 18 | AI83: 3 | AJ83: 1 | AK83: 80 | AL83: 0 | AM83: 6 | AN83: 3 | AO83: 6 | AP83: 4 | AQ83: 0 | AR83: 4
... A90: No | B90: Travel_Rarely | C90: 25 - 34 | D90: Current Employees | E90: R&D | F90: Life Sciences | G90: STAFF-117 | H90: 117 | I90: Male | J90: Healthcare Representative | K90: Married | L90: No | M90: Y | N90: 3 | O90: -2 | P90: 0 | Q90: 30 | R90: 0 | T90: 0 | U90: 1 | V90: 288 | W90: 2 | X90: Bachelor's Degree | Y90: 1 | Z90: 3 | AA90: 99 | AB90: 2 | AC90: 2 | AD90: 2 | AE90: 4152 | AF90: 15830 | AG90: 1 | AH90: 19 | AI90: 3 | AJ90: 1 | AK90: 80 | AL90: 3 | AM90: 11 | AN90: 3 | AO90: 11 | AP90: 10 | AQ90: 10 | AR90: 8
A91: Yes | B91: Travel_Rarely | C91: 45 - 54 | D91: Ex-Employees | E91: Sales | F91: Medical | G91: STAFF-118 | H91: 118 | I91: Male | J91: Sales Executive | K91: Single | L91: No | M91: Y | N91: 3 | O91: -2 | P91: 0 | Q91: 46 | R91: 1 | S91: 1 | T91: 1 | U91: 0 | V91: 669 | W91: 9 | X91: Associates Degree | Y91: 1 | Z91: 3 | AA91: 64 | AB91: 2 | AC91: 3 | AD91: 4 | AE91: 9619 | AF91: 13596 | AG91: 1 | AH91: 16 | AI91: 3 | AJ91: 4 | AK91: 80 | AL91: 0 | AM91: 9 | AN91: 3 | AO91: 9 | AP91: 8 | AQ91: 4 | AR91: 7
A92: No | B92: Travel_Frequently | C92: 35 - 44 | D92: Current Employees | E92: R&D | F92: Life Sciences | G92: STAFF-119 | H92: 119 | I92: Male | J92: Healthcare Representative | K92: Married | L92: No | M92: Y | N92: 3 | O92: -2 | P92: 0 | Q92: 40 | R92: 0 | T92: 0 | U92: 1 | V92: 530 | W92: 1 | X92: Master's Degree | Y92: 1 | Z92: 3 | AA92: 78 | AB92: 2 | AC92: 4 | AD92: 2 | AE92: 13503 | AF92: 14115 | AG92: 1 | AH92: 22 | AI92: 4 | AJ92: 4 | AK92: 80 | AL92: 1 | AM92: 22 | AN92: 2 | AO92: 22 | AP92: 3 | AQ92: 11 | AR92: 11
A93: No | B93: Travel_Rarely | C93: 45 - 54 | D93: Current Employees | E93: Sales | F93: Marketing | G93: STAFF-120 | H93: 120 | I93: Male | J93: Sales Executive | K93: Single | L93: Yes | M93: Y | N93: 2 | O93: -2 | P93: 0 | Q93: 51 | R93: 0 | T93: 0 | U93: 1 | V93: 632 | W93: 21 | X93: Master's Degree | Y93: 1 | Z93: 3 | AA93: 71 | AB93: 3 | AC93: 2 | AD93: 4 | AE93: 5441 | AF93: 8423 | AG93: 0 | AH93: 22 | AI93: 4 | AJ93: 4 | AK93: 80 | AL93: 0 | AM93: 11 | AN93: 1 | AO93: 10 | AP93: 7 | AQ93: 1 | AR93: 0
A94: No | B94: Travel_Rarely | C94: 25 - 34 | D94: Current Employees | E94: Sales | F94: Medical | G94: STAFF-121 | H94: 121 | I94: Female | J94: Sales Executive | K94: Divorced | L94: Yes | M94: Y | N94: 4 | O94: -2 | P94: 0 | Q94: 30 | R94: 0 | T94: 0 | U94: 1 | V94: 1334 | W94: 4 | X94: Associates Degree | Y94: 1 | Z94: 3 | AA94: 63 | AB94: 2 | AC94: 2 | AD94: 3 | AE94: 5209 | AF94: 19760 | AG94: 1 | AH94: 12 | AI94: 3 | AJ94: 2 | AK94: 80 | AL94: 3 | AM94: 11 | AN94: 2 | AO94: 11 | AP94: 8 | AQ94: 2 | AR94: 7
A95: No | B95: Travel_Frequently | C95: 45 - 54 | D95: Current Employees | E95: R&D | F95: Medical | G95: STAFF-124 | H95: 124 | I95: Male | J95: Healthcare Representative | K95: Married | L95: Yes | M95: Y | N95: 5 | O95: -2 | P95: 0 | Q95: 46 | R95: 0 | T95: 0 | U95: 1 | V95: 638 | W95: 1 | X95: Bachelor's Degree | Y95: 1 | Z95: 3 | AA95: 40 | AB95: 2 | AC95: 3 | AD95: 4 | AE95: 10673 | AF95: 3142 | AG95: 2 | AH95: 13 | AI95: 3 | AJ95: 3 | AK95: 80 | AL95: 1 | AM95: 21 | AN95: 2 | AO95: 10 | AP95: 9 | AQ95: 9 | AR95: 5
A96: No | B96: Travel_Rarely | C96: 25 - 34 | D96: Current Employees | E96: Sales | F96: Medical | G96: STAFF-125 | H96: 125 | I96: Male | J96: Sales Executive | K96: Single | L96: No | M96: Y | N96: 0 | O96: -2 | P96: 0 | Q96: 32 | R96: 0 | T96: 0 | U96: 1 | V96: 1093 | W96: 6 | X96: Master's Degree | Y96: 1 | Z96: 2 | AA96: 87 | AB96: 3 | AC96: 2 | AD96: 3 | AE96: 5010 | AF96: 24301 | AG96: 1 | AH96: 16 | AI96: 3 | AJ96: 1 | AK96: 80 | AL96: 0 | AM96: 12 | AN96: 3 | AO96: 11 | AP96: 8 | AQ96: 5 | AR96: 7
A97: No | B97: Travel_Rarely | C97: 45 - 54 | D97: Current Employees | E97: R&D | F97: Technical Degree | G97: STAFF-126 | H97: 126 | I97: Female | J97: Research Director | K97: Married | L97: No | M97: Y | N97: 5 | O97: -2 | P97: 0 | Q97: 54 | R97: 0 | T97: 0 | U97: 1 | V97: 1217 | W97: 2 | X97: Master's Degree | Y97: 1 | Z97: 1 | AA97: 60 | AB97: 3 | AC97: 3 | AD97: 3 | AE97: 13549 | AF97: 24001 | AG97: 9 | AH97: 12 | AI97: 3 | AJ97: 1 | AK97: 80 | AL97: 1 | AM97: 16 | AN97: 1 | AO97: 4 | AP97: 3 | AQ97: 0 | AR97: 3
A98: No | B98: Travel_Rarely | C98: Under 25 | D98: Current Employees | E98: Sales | F98: Other | G98: STAFF-128 | H98: 128 | I98: Female | J98: Sales Executive | K98: Married | L98: No | M98: Y | N98: 2 | O98: -2 | P98: 0 | Q98: 24 | R98: 0 | T98: 0 | U98: 1 | V98: 1353 | W98: 3 | X98: Associates Degree | Y98: 1 | Z98: 1 | AA98: 33 | AB98: 3 | AC98: 2 | AD98: 3 | AE98: 4999 | AF98: 17519 | AG98: 0 | AH98: 21 | AI98: 4 | AJ98: 1 | AK98: 80 | AL98: 1 | AM98: 4 | AN98: 2 | AO98: 3 | AP98: 2 | AQ98: 0 | AR98: 2
A99: No | B99: Non-Travel | C99: 25 - 34 | D99: Current Employees | E99: Sales | F99: Medical | G99: STAFF-129 | H99: 129 | I99: Male | J99: Sales Executive | K99: Married | L99: No | M99: Y | N99: 3 | O99: -2 | P99: 0 | Q99: 28 | R99: 0 | T99: 0 | U99: 1 | V99: 120 | W99: 4 | X99: Bachelor's Degree | Y99: 1 | Z99: 2 | AA99: 43 | AB99: 3 | AC99: 2 | AD99: 3 | AE99: 4221 | AF99: 8863 | AG99: 1 | AH99: 15 | AI99: 3 | AJ99: 2 | AK99: 80 | AL99: 0 | AM99: 5 | AN99: 4 | AO99: 5 | AP99: 4 | AQ99: 0 | AR99: 4
A100: No | B100: Travel_Rarely | C100: Over 55 | D100: Current Employees | E100: Sales | F100: Medical | G100: STAFF-131 | H100: 131 | I100: Male | J100: Sales Executive | K100: Single | L100: No | M100: Y | N100: 1 | O100: -2 | P100: 0 | Q100: 58 | R100: 0 | T100: 0 | U100: 1 | V100: 682 | W100: 10 | X100: Master's Degree | Y100: 1 | Z100: 4 | AA100: 37 | AB100: 3 | AC100: 4 | AD100: 3 | AE100: 13872 | AF100: 24409 | AG100: 0 | AH100: 13 | AI100: 3 | AJ100: 3 | AK100: 80 | AL100: 0 | AM100: 38 | AN100: 2 | AO100: 37 | AP100: 10 | AQ100: 1 | AR100: 8
A101: No | B101: Non-Travel | C101: 35 - 44 | D101: Current Employees | E101: R&D | F101: Medical | G101: STAFF-132 | H101: 132 | I101: Male | J101: Laboratory Technician | K101: Married | L101: No | M101: Y | N101: 3 | O101: -2 | P101: 0 | Q101: 44 | R101: 0 | T101: 0 | U101: 1 | V101: 489 | W101: 23 | X101: Bachelor's Degree | Y101: 1 | Z101: 2 | AA101: 67 | AB101: 3 | AC101: 2 | AD101: 3 | AE101: 2042 | AF101: 25043 | AG101: 4 | AH101: 12 | AI101: 3 | AJ101: 3 | AK101: 80 | AL101: 1 | AM101: 17 | AN101: 4 | AO101: 3 | AP101: 2 | AQ101: 1 | AR101: 2
A102: Yes | B102: Travel_Rarely | C102: 35 - 44 | D102: Ex-Employees | E102: HR | F102: Human Resources | G102: STAFF-133 | H102: 133 | I102: Male | J102: Human Resources | K102: Divorced | L102: Yes | M102: Y | N102: 3 | O102: -2 | P102: 0 | Q102: 37 | R102: 1 | S102: 1 | T102: 1 | U102: 0 | V102: 807 | W102: 6 | X102: Master's Degree | Y102: 1 | Z102: 3 | AA102: 63 | AB102: 3 | AC102: 1 | AD102: 4 | AE102: 2073 | AF102: 23648 | AG102: 4 | AH102: 22 | AI102: 4 | AJ102: 4 | AK102: 80 | AL102: 0 | AM102: 7 | AN102: 3 | AO102: 3 | AP102: 2 | AQ102: 0 | AR102: 2
A103: No | B103: Travel_Rarely | C103: 25 - 34 | D103: Current Employees | E103: R&D | F103: Life Sciences | G103: STAFF-134 | H103: 134 | I103: Male | J103: Research Scientist | K103: Single | L103: No | M103: Y | N103: 2 | O103: -2 | P103: 0 | Q103: 32 | R103: 0 | T103: 0 | U103: 1 | V103: 827 | W103: 1 | X103: High School | Y103: 1 | Z103: 4 | AA103: 71 | AB103: 3 | AC103: 1 | AD103: 2 | AE103: 2956 | AF103: 15178 | AG103: 1 | AH103: 13 | AI103: 3 | AJ103: 4 | AK103: 80 | AL103: 0 | AM103: 1 | AN103: 3 | AO103: 1 | AP103: 0 | AQ103: 0 | AR103: 0
A104: Yes | B104: Travel_Frequently | C104: Under 25 | D104: Ex-Employees | E104: R&D | F104: Life Sciences | G104: STAFF-137 | H104: 137 | I104: Female | J104: Laboratory Technician | K104: Single | L104: Yes | M104: Y | N104: 5 | O104: -2 | P104: 0 | Q104: 20 | R104: 1 | S104: 1 | T104: 1 | U104: 0 | V104: 871 | W104: 6 | X104: Bachelor's Degree | Y104: 1 | Z104: 4 | AA104: 66 | AB104: 2 | AC104: 1 | AD104: 2 | AE104: 2926 | AF104: 19783 | AG104: 1 | AH104: 18 | AI104: 3 | AJ104: 2 | AK104: 80 | AL104: 0 | AM104: 1 | AN104: 3 | AO104: 1 | AP104: 0 | AQ104: 1 | AR104: 0
A105: No | B105: Travel_Rarely | C105: 25 - 34 | D105: Current Employees | E105: R&D | F105: Other | G105: STAFF-138 | H105: 138 | I105: Female | J105: Research Scientist | K105: Single | L105: No | M105: Y | N105: 3 | O105: -2 | P105: 0 | Q105: 34 | R105: 0 | T105: 0 | U105: 1 | V105: 665 | W105: 6 | X105: Master's Degree | Y105: 1 | Z105: 1 | AA105: 41 | AB105: 3 | AC105: 2 | AD105: 3 | AE105: 4809 | AF105: 12482 | AG105: 1 | AH105: 14 | AI105: 3 | AJ105: 3 | AK105: 80 | AL105: 0 | AM105: 16 | AN105: 3 | AO105: 16 | AP105: 13 | AQ105: 2 | AR105: 10
A106: No | B106: Non-Travel | C106: 35 - 44 | D106: Current Employees | E106: R&D | F106: Life Sciences | G106: STAFF-139 | H106: 139 | I106: Male | J106: Healthcare Representative | K106: Divorced | L106: No | M106: Y | N106: 2 | O106: -2 | P106: 0 | Q106: 37 | R106: 0 | T106: 0 | U106: 1 | V106: 1040 | W106: 2 | X106: Associates Degree | Y106: 1 | Z106: 3 | AA106: 100 | AB106: 2 | AC106: 2 | AD106: 2 | AE106: 5163 | AF106: 15850 | AG106: 5 | AH106: 14 | AI106: 3 | AJ106: 4 | AK106: 80 | AL106: 1 | AM106: 17 | AN106: 4 | AO106: 1 | AP106: 0 | AQ106: 0 | AR106: 0
A107: No | B107: Non-Travel | C107: Over 55 | D107: Current Employees | E107: HR | F107: Human Resources | G107: STAFF-140 | H107: 140 | I107: Female | J107: Manager | K107: Married | L107: No | M107: Y | N107: 3 | O107: -2 | P107: 0 | Q107: 59 | R107: 0 | T107: 0 | U107: 1 | V107: 1420 | W107: 2 | X107: Master's Degree | Y107: 1 | Z107: 3 | AA107: 32 | AB107: 2 | AC107: 5 | AD107: 4 | AE107: 18844 | AF107: 21922 | AG107: 9 | AH107: 21 | AI107: 4 | AJ107: 4 | AK107: 80 | AL107: 1 | AM107: 30 | AN107: 3 | AO107: 3 | AP107: 2 | AQ107: 2 | AR107: 2
A108: No | B108: Travel_Frequently | C108: 45 - 54 | D108: Current Employees | E108: R&D | F108: Life Sciences | G108: STAFF-141 | H108: 141 | I108: Female | J108: Research Director | K108: Married | L108: Yes | M108: Y | N108: 1 | O108: -2 | P108: 0 | Q108: 50 | R108: 0 | T108: 0 | U108: 1 | V108: 1115 | W108: 1 | X108: Bachelor's Degree | Y108: 1 | Z108: 1 | AA108: 73 | AB108: 3 | AC108: 5 | AD108: 2 | AE108: 18172 | AF108: 9755 | AG108: 3 | AH108: 19 | AI108: 3 | AJ108: 1 | AK108: 80 | AL108: 0 | AM108: 28 | AN108: 2 | AO108: 8 | AP108: 3 | AQ108: 0 | AR108: 7
A109: Yes | B109: Travel_Rarely | C109: 25 - 34 | D109: Ex-Employees | E109: Sales | F109: Marketing | G109: STAFF-142 | H109: 142 | I109: Male | J109: Sales Executive | K109: Single | L109: Yes | M109: Y | N109: 1 | O109: -2 | P109: 0 | Q109: 25 | R109: 1 | S109: 1 | T109: 1 | U109: 0 | V109: 240 | W109: 5 | X109: Bachelor's Degree | Y109: 1 | Z109: 3 | AA109: 46 | AB109: 2 | AC109: 2 | AD109: 3 | AE109: 5744 | AF109: 26959 | AG109: 1 | AH109: 11 | AI109: 3 | AJ109: 4 | AK109: 80 | AL109: 0 | AM109: 6 | AN109: 3 | AO109: 6 | AP109: 4 | AQ109: 0 | AR109: 3
A110: No | B110: Travel_Rarely | C110: 25 - 34 | D110: Current Employees | E110: R&D | F110: Medical | G110: STAFF-143 | H110: 143 | I110: Male | J110: Research Scientist | K110: Married | L110: No | M110: Y | N110: 2 | O110: -2 | P110: 0 | Q110: 25 | R110: 0 | T110: 0 | U110: 1 | V110: 1280 | W110: 7 | X110: High School | Y110: 1 | Z110: 4 | AA110: 64 | AB110: 2 | AC110: 1 | AD110: 4 | AE110: 2889 | AF110: 26897 | AG110: 1 | AH110: 11 | AI110: 3 | AJ110: 3 | AK110: 80 | AL110: 2 | AM110: 2 | AN110: 3 | AO110: 2 | AP110: 2 | AQ110: 2 | AR110: 1
...

Sheet Images

Sheet Background 1

Sheet Background 2

Sheet Background 3

Sheet Dashboard

Sheet EmployeeLookup
A1: Employee Lookup (type an Employee Number in B2)
A2: Employee Number | B2: 4
A3: Department | B3: =INDEX(Data!$E$2:$E$1471,MATCH($B$2,Data!$H$2:$H$1471,0)) -> R&D
A4: Job Role | B4: =INDEX(Data!$J$2:$J$1471,MATCH($B$2,Data!$H$2:$H$1471,0)) -> Laboratory Technician
A5: Attrition (Yes/No) | B5: =INDEX(Data!$A$2:$A$1471,MATCH($B$2,Data!$H$2:$H$1471,0)) -> Yes
A6: Monthly Income | B6: =INDEX(Data!$AE$2:$AE$1471,MATCH($B$2,Data!$H$2:$H$1471,0)) -> 2090
A7: Years At Company | B7: =INDEX(Data!$AO$2:$AO$1471,MATCH($B$2,Data!$H$2:$H$1471,0)) -> 0
A8: Dept Attrition Rate (Benchmark) | B8: =INDEX($D$11:$D$13,MATCH(B3,$A$11:$A$13,0)) -> 0.1383975
A10: Department | B10: Headcount | C10: Attrition Count | D10: Attrition Rate
A11: HR | B11: =COUNTIF(Data!$E$2:$E$1471,A11) -> 63 | C11: =SUMIFS(Data!$R$2:$R$1471,Data!$E$2:$E$1471,A11) -> 12 | D11: =C11/B11 -> 0.19047619
A12: R&D | B12: =COUNTIF(Data!$E$2:$E$1471,A12) -> 961 | C12: =SUMIFS(Data!$R$2:$R$1471,Data!$E$2:$E$1471,A12) -> 133 | D12: =C12/B12 -> 0.1383975
A13: Sales | B13: =COUNTIF(Data!$E$2:$E$1471,A13) -> 446 | C13: =SUMIFS(Data!$R$2:$R$1471,Data!$E$2:$E$1471,A13) -> 92 | D13: =C13/B13 -> 0.20627803
A14: Grand Total | B14: =SUM(B11:B13) -> 1470 | C14: =SUM(C11:C13) -> 237 | D14: =C14/B14 -> 0.16122449
